LICENSE
MANIFEST.in
README.md
setup.cfg
setup.py
upddetect/__init__.py
upddetect/upddetect.py
upddetect/variables.py
upddetect.egg-info/PKG-INFO
upddetect.egg-info/SOURCES.txt
upddetect.egg-info/dependency_links.txt
upddetect.egg-info/entry_points.txt
upddetect.egg-info/requires.txt
upddetect.egg-info/top_level.txt
upddetect/common/__init__.py
upddetect/common/registry.py
upddetect/packet_managers/__init__.py
upddetect/packet_managers/apt.py
upddetect/packet_managers/general.py
upddetect/packet_managers/pip.py